{
  "AR-B": 3,
  "AR-C": 3,
  "AR-X": 3,
  "AR-S": 3,
  "AR-OTHER": 3,

  "AU-NSW": 3,
  "AU-VIC": 4,
  "AU-QLD": 1,
  "AU-SA": 3,
  "AU-WA": 3,
  "AU-TAS": 5,
  "AU-NT": 1,
  "AU-ACT": 4,

  "BR-SP": 2,
  "BR-RJ": 1,
  "BR-MG": 2,
  "BR-RS": 3,
  "BR-OTHER": 1,

  "CA-BC": 5,
  "CA-AB": 7,
  "CA-SK": 7,
  "CA-MB": 7,
  "CA-ON": 6,
  "CA-QC": 7,
  "CA-NS": 6,
  "CA-OTHER": 7,

  "CN-GD": 3,
  "CN-SH": 3,
  "CN-BJ": 4,
  "CN-SD": 4,
  "CN-JS": 3,
  "CN-SC": 4,
  "CN-OTHER": 4,

  "FR-IDF": 4,
  "FR-ARA": 4,
  "FR-NAQ": 4,
  "FR-OTHER": 4,

  "DE-NW": 5,
  "DE-BY": 5,
  "DE-BW": 5,
  "DE-OTHER": 5,

  "IN-MH": 1,
  "IN-DL": 2,
  "IN-KA": 1,
  "IN-TN": 1,
  "IN-GJ": 1,
  "IN-UP": 2,
  "IN-RJ": 2,
  "IN-WB": 1,
  "IN-AP": 1,
  "IN-TS": 1,
  "IN-KL": 1,
  "IN-PB": 2,
  "IN-HR": 2,
  "IN-OR": 1,
  "IN-OTHER": 1,

  "ID-JK": 1,
  "ID-JW": 1,
  "ID-SU": 1,
  "ID-KA": 1,
  "ID-OTHER": 1,

  "IT-LOM": 4,
  "IT-LAZ": 4,
  "IT-CAM": 4,
  "IT-OTHER": 4,

  "JP-13": 4,
  "JP-27": 4,
  "JP-23": 4,
  "JP-01": 6,
  "JP-OTHER": 5,

  "MX-CMX": 2,
  "MX-JAL": 2,
  "MX-NLE": 2,
  "MX-OTHER": 2,

  "RU-MOW": 6,
  "RU-SPE": 6,
  "RU-SIB": 7,
  "RU-OTHER": 7,

  "SA-RD": 1,
  "SA-MK": 1,
  "SA-SH": 1,
  "SA-OTHER": 1,

  "ZA-GP": 3,
  "ZA-WC": 3,
  "ZA-KZN": 2,
  "ZA-OTHER": 3,

  "KR-11": 4,
  "KR-26": 4,
  "KR-28": 4,
  "KR-OTHER": 4,

  "TR-34": 3,
  "TR-06": 4,
  "TR-35": 3,
  "TR-OTHER": 4,

  "GB-ENG": 5,
  "GB-SCT": 5,
  "GB-WLS": 5,
  "GB-NIR": 5,

  "US-CAMX": 3,
  "US-ERCT": 2,
  "US-FRCC": 2,
  "US-MROE": 6,
  "US-MROW": 6,
  "US-NEWE": 5,
  "US-NWPP": 5,
  "US-RFCE": 4,
  "US-RFCM": 6,
  "US-RFCW": 4,
  "US-SRSO": 3,
  "US-OTHER": 4
}
